botboy/__init__.py
botboy/core.py
botboy/tests/__init__.py
botboy/tests/botboy_tests.py
botboy-3.0.3.dist-info/LICENSE
botboy-3.0.3.dist-info/WHEEL
botboy-3.0.3.dist-info/METADATA
botboy-3.0.3.dist-info/RECORD
