Metadata-Version: 2.1
Name: botboy
Version: 3.0.3
Summary: Multithreading & processing worker and Sequencer
Author-email: Marques Traylor <traylorboy@proton.me>
Classifier: License :: OSI Approved :: MIT License
Project-URL: Home, https://github.com/TraylorBoy/BotBoy
